
[
	{
		"spread": "One Card",
		"cards": ["Card"],
		"image": "https://emfobsnlxploca6s.public.blob.vercel-storage.com/images/spreads/one-card.png",
		"numberofCards": 1
	},
    {
        "spread": "Two Card (Situation/Advice)",
        "cards": ["Situation", "Advice"],
        "image": "https://emfobsnlxploca6s.public.blob.vercel-storage.com/images/spreads/two-cardsa.png",
        "numberofCards": 2	
    },
    {
        "spread": "Two Card (Pros/Cons)",
        "cards": ["Pros", "Cons"],
        "image": "https://emfobsnlxploca6s.public.blob.vercel-storage.com/images/spreads/two-cardspc.png",
        "numberofCards": 2
    },
    {
        "spread": "Two Card (Yes/No)",
        "cards": ["Yes", "No"],
        "image": "https://emfobsnlxploca6s.public.blob.vercel-storage.com/images/spreads/two-cardsyn.png",
        "numberofCards": 2											
    },
	{
		"spread": "Three Card (Past/Present/Future)",
		"cards": ["Past", "Present", "Future"],
		"image": "https://emfobsnlxploca6s.public.blob.vercel-storage.com/images/spreads/three-cardppf.png",
		"numberofCards": 3
	},
    {
		"spread": "Three Card (Within, Without, Advice)",
		"cards": ["Within", "Without", "Advice"],
		"image": "https://emfobsnlxploca6s.public.blob.vercel-storage.com/images/spreads/three-cardwwa.png",
		"numberofCards": 3	
	},
    {
		"spread": "Three Card (Body, Mind, Spirit)",
		"cards": ["Body", "Mind", "Spirit"],
		"image": "https://emfobsnlxploca6s.public.blob.vercel-storage.com/images/spreads/three-cardbms.png",
		"numberofCards": 3
	},
    {
		"spread": "Three Card (Energy, Obstacle, Advice)",
		"cards": ["Energy", "Obstacle", "Advice"],
		"image": "https://emfobsnlxploca6s.public.blob.vercel-storage.com/images/spreads/three-cardeoa.png",
		"numberofCards": 3			
	},
    {
		"spread": "Four Card Guidance",
		"cards": ["Heart of Issue", "Internal Influences", "External Influences", "Key to a Favorable Outcome"],
		"image": "https://emfobsnlxploca6s.public.blob.vercel-storage.com/images/spreads/four-card-guidance.png",
		"numberofCards": 4
	},
	{
		"spread": "Celtic Cross",
		"cards": [
			"Significator",
			"Crossing",
			"Foundation",
			"Recent Past",
			"Crowning",
			"Near Future",
			"Self",
			"Environment",
			"Hopes/Fears",
			"Outcome"
		],
		"image": "https://emfobsnlxploca6s.public.blob.vercel-storage.com/images/spreads/celtic-cross.png",
		"numberofCards": 10
	},
	{
		"spread": "Horseshoe",
		"cards": [
			"Past",
			"Present",
			"Hidden Influences",
			"Obstacle",
			"External Influences",
			"Best Course of Action",
			"Outcome"
		],
		"image": "https://emfobsnlxploca6s.public.blob.vercel-storage.com/images/spreads/horseshoe.png",
		"numberofCards": 7
	},
	{
		"spread": "Relationship Five",
		"cards": ["You", "Partner", "Strengths", "Weaknesses", "Outcome"],
		"image": "https://emfobsnlxploca6s.public.blob.vercel-storage.com/images/spreads/relationship-five.png",
		"numberofCards": 5
	}
]
